LICENSE
README.md
setup.py
src/backtest/LICENSE
src/backtest/__init__.py
src/backtest/__version__.py
src/backtest/help.txt
src/backtest/main.py
src/backtest/version.txt
src/backtest/cli/__init__.py
src/backtest/cli/cliapp.py
src/backtest/cli/cron.py
src/backtest/cli/show.py
src/backtest/cli/template.py
src/backtest/cli/template/main.py
src/backtest/cli/template/release.py
src/backtest/cli/template/data/__init__.py
src/backtest/cli/template/indicators/__init__.py
src/backtest/data/README.md
src/backtest/data/__init__.py
src/backtest/data/datapipe.py
src/backtest/data/json_extension.py
src/backtest/data/pipes.py
src/backtest/data/utils.py
src/backtest/engine/__init__.py
src/backtest/engine/account.py
src/backtest/engine/analyser.py
src/backtest/engine/backtest.py
src/backtest/engine/backtestResult.py
src/backtest/engine/broker.py
src/backtest/engine/cashController.py
src/backtest/engine/functional.py
src/backtest/engine/metadata.py
src/backtest/engine/portfolio.py
src/backtest/engine/record.py
src/backtest/engine/strategy.py
src/backtest/engine/time_resolution_extenders.py
src/backtest/engine/trade.py
src/backtest/engine/transaction.py
src/backtest/engine/tsData.py
src/backtest/engine/utils.py
src/backtest/indicators/__init__.py
src/backtest/indicators/indicator.py
src/backtest/indicators/indicatorSet.py
src/backtest/indicators/prebuilt.py
src/backtest/serve/__init__.py
src/backtest/serve/job.py
src/backtest/serve/renderer.py
src/backtest/serve/state_signals.py
src/backtest/serve/stats_calculator.py
src/backtest/serve/renderers/__init__.py
src/backtest/serve/renderers/email_renderer.py
src/backtest/serve/renderers/html_renderer.py
src/backtest/serve/renderers/json_renderer.py
src/backtest/serve/renderers/log_renderer.py
src/backtest/serve/renderers/markup_renderer.py
src/backtest/serve/renderers/pdf_renderer.py
src/backtest/serve/renderers/html_templates/dark.css
src/backtest/serve/renderers/html_templates/light.css
src/backtest_pro.egg-info/PKG-INFO
src/backtest_pro.egg-info/SOURCES.txt
src/backtest_pro.egg-info/dependency_links.txt
src/backtest_pro.egg-info/entry_points.txt
src/backtest_pro.egg-info/requires.txt
src/backtest_pro.egg-info/top_level.txt