Metadata-Version: 2.1
Name: backtest-pro
Version: 0.1.1
Summary: A feature-rich event driven backtesting framework
Home-page: https://github.com/anthol42/backtestPro
Author: Anthony Lavertu
Author-email: alavertu2@gmail.com
Project-URL: Issues, https://github.com/anthol42/backtestPro/issues
Keywords: backtest-pro,backtestpro,backtest,pybacktest,py-backtest,backtesting,quant,finance,stocks,crypto,cryptocurrency,derivatives,trading,investing,financial,technical,fundamental,ai,machine,learning,neural,network,deep,reinforcement,algorithm,strategy,portfolio,optimization,risk,management
Classifier: Programming Language :: Python :: 3
Classifier: Operating System :: OS Independent
Classifier: Development Status :: 3 - Alpha
Classifier: Intended Audience :: Financial and Insurance Industry
Classifier: Intended Audience :: Science/Research
Classifier: Intended Audience :: Education
Classifier: Topic :: Office/Business :: Financial :: Investment
Classifier: Topic :: Scientific/Engineering :: Artificial Intelligence
Requires-Python: >=3.8
License-File: LICENSE
Requires-Dist: pandas>=2.2.0
Requires-Dist: numpy>=1.26.4
Requires-Dist: matplotlib>=3.8.0
Requires-Dist: psutil>=5.9.0
Requires-Dist: py-cpuinfo>=9.0.0
Requires-Dist: mplfinance>=0.12.10b0
Requires-Dist: tqdm>=4.66.0
Requires-Dist: yfinance>=0.2.37
Provides-Extra: optional
Requires-Dist: TA-Lib>=0.4.0; extra == "optional"
Requires-Dist: plotly>=5.20.0; extra == "optional"
Requires-Dist: schedule>=1.2.0; extra == "optional"
Requires-Dist: kaleido>=0.2.1; extra == "optional"
Requires-Dist: weasyprint>=61.2; extra == "optional"
Requires-Dist: python-crontab>=3.0.0; extra == "optional"
